{
  "id": "10-soft-hospitality",
  "slug": "10-soft-hospitality",
  "name": "柔らかなホスピタリティ",
  "references": [
    "global/airbnb",
    "jp/cybozu"
  ],
  "structures": {
    "home": "brochure",
    "lookbook": "notebook",
    "about": "storybook"
  },
  "assets": {
    "heroVisual": {
      "src": "./assets/generated/variants/10-soft-hospitality-hero.png",
      "alt": "Soft Hospitality のために設計したヒーロー用コンセプトビジュアル",
      "caption": "メインビジュアル / 柔らかなホスピタリティ"
    },
    "featureImage": {
      "src": "./assets/generated/variants/top-home-portrait/10-soft-hospitality.png",
      "alt": "Soft Hospitality のトップページ導入用に追加した縦長素材",
      "caption": "代表ルック補助 / 柔らかなホスピタリティ"
    },
    "ルック資料Spotlight": {
      "src": "./assets/generated/variants/square/10-soft-hospitality.png",
      "alt": "Soft Hospitality のルックブックを補強する正方形のエディトリアル素材",
      "caption": "ルック補助 / 柔らかなホスピタリティ"
    },
    "aboutStoryImage": {
      "src": "./assets/generated/variants/portrait/10-soft-hospitality.png",
      "alt": "Soft Hospitality の制作背景を補強する縦長のエディトリアル素材",
      "caption": "制作背景補助 / 柔らかなホスピタリティ"
    },
    "homeGallery": [
      {
        "src": "./assets/generated/variants/square/10-soft-hospitality.png",
        "alt": "Soft Hospitality のトップページ用に配置した正方形素材",
        "caption": "補助カット 01 / 柔らかなホスピタリティ",
        "tone": "square"
      },
      {
        "src": "./assets/generated/variants/top-home-landscape/10-soft-hospitality.png",
        "alt": "Soft Hospitality のトップページ中央に配置する横長素材",
        "caption": "補助カット 02 / 柔らかなホスピタリティ",
        "tone": "wide"
      },
      {
        "src": "./assets/generated/variants/portrait/10-soft-hospitality.png",
        "alt": "Soft Hospitality のトップページ右側に配置する縦長素材",
        "caption": "補助カット 03 / 柔らかなホスピタリティ",
        "tone": "tall"
      }
    ],
    "aboutGallery": [
      {
        "src": "./assets/generated/variants/10-soft-hospitality-hero.png",
        "alt": "Soft Hospitality の空気感を横方向に補うビジュアル",
        "caption": "制作風景 01 / 柔らかなホスピタリティ"
      },
      {
        "src": "./assets/generated/variants/portrait/10-soft-hospitality.png",
        "alt": "Soft Hospitality の制作温度を補う縦長素材",
        "caption": "制作風景 02 / 柔らかなホスピタリティ"
      }
    ]
  },
  "content": {
    "brand": {
      "label": "冊子型ホスピタリティ資料",
      "tagline": "やわらかな歓迎ムードで迎え入れる、親しみのある静けさ。",
      "summary": "AUN をもっとも迎え入れる印象で見せる案です。構えずに読めることを優先し、接客の入口をやさしく整えています。",
      "themeTitle": "ひらかれたテーブル / 第1章",
      "seasonHeading": "温度のある写真とやわらかい導線で、会話を開く構成。",
      "seasonCopy": "この案では、強い緊張感よりも会話の始まりやすさを優先します。売場でも資料でも、相手が一歩入りやすいことを価値としています。",
      "audience": "接客導線をやわらかくしたいセレクト、生活圏に近い媒体、親しみやすい空気を求めるスタイリスト。",
      "priceCue": "入りやすさのある上質帯。ラグジュアリーすぎず、親しみを保つ価格感です。",
      "partnerItems": [
        {
          "title": "取扱のご相談",
          "text": "温度のやわらかい言葉で整えたラインシートを共有します。",
          "href": "mailto:partners@aun-studio.example?subject=AUN%20Stockist%20Inquiry"
        },
        {
          "title": "掲載・取材",
          "text": "媒体にそのまま載せやすい、やさしい温度の掲載文を案内します。",
          "href": "mailto:press@aun-studio.example?subject=AUN%20Press%20Request"
        },
        {
          "title": "協業のご相談",
          "text": "空間演出やもてなしの文脈に寄せた協業に向いています。",
          "href": "mailto:hello@aun-studio.example?subject=AUN%20Collaboration"
        }
      ]
    },
    "home": {
      "reasons": [
        {
          "title": "最初の会話が始めやすい",
          "text": "最初の一歩を軽くし、会話に入りやすくします。"
        },
        {
          "title": "売場の緊張をやわらげる",
          "text": "緊張感の強い売場にも、やわらかな入口をつくれます。"
        },
        {
          "title": "抽象より人の温度が先に立つ",
          "text": "概念より先に、人が着る像として受け取られやすい案です。"
        }
      ],
      "representativeLook": {
        "title": "代表ルック / 会話を開く穏やかなロングコート",
        "summary": "代表ルックも威圧感より親しみのある整い方で見せます。接客や紹介の一言目が穏やかになる構成です。",
        "details": [
          "生活圏に近い媒体でも扱いやすい印象です。",
          "売場の入口に置いても緊張を上げすぎません。",
          "静かな上質感を保ちながら距離を縮めます。"
        ]
      }
    },
    "collections": [
      {
        "id": "resonant-quiet",
        "title": "ひらかれたテーブル / 第1章",
        "summary": "静けさを保ちつつ、人の気配を感じやすくした基幹ラインです。",
        "noteTitle": "補足ノート / ひらかれたテーブル",
        "note": "強く押し切るより、長く会話を続けられる空気を重視したラインです。接客の柔らかさがそのまま価値になります。",
        "selectedPieces": [
          {
            "name": "主力バイアスコート",
            "descriptor": "入口に置きやすい、やさしい主力コート。"
          },
          {
            "name": "ヴェールシャツ",
            "descriptor": "全体を親しみやすく整える核シャツ。"
          },
          {
            "name": "テーパードラップスカート",
            "descriptor": "動きに軽さを足す、扱いやすいボトム。"
          }
        ],
        "label": "ひらかれたテーブル"
      },
      {
        "id": "counterlight",
        "title": "温度の補助線 / 補助編集",
        "summary": "さらに親しみを足すための、明るい補助ラインです。",
        "noteTitle": "補足ノート / 温度の補助線",
        "note": "売場の温度を少しだけ上げたいときに使う中間色で、会話の始まりを助けます。",
        "selectedPieces": [
          {
            "name": "灰青コート",
            "descriptor": "導入の一体として置きやすい暖色寄りのコート。"
          },
          {
            "name": "ドライベスト",
            "descriptor": "硬さをほぐしてレイヤーを増やせる補助ピース。"
          }
        ],
        "label": "温度の補助線"
      }
    ],
    "about": {
      "intro": "AUN を最も人に近い距離で見せる案です。服の前に、相手との会話が始まりやすいことを優先しています。",
      "story": {
        "title": "閉じたサロンではなく、招き入れる冊子として組んだライン。",
        "copy": "少量制作の精度は保ちながら、見え方だけを柔らかくします。初見の構えを下げて、静かな好感を残すための案です。",
        "points": [
          "営業資料は安心感のある書き方で整えます。",
          "掲載用にもやわらかい温度の短文を用意します。",
          "仮ビジュアルでも、人が近づきやすい温度を優先します。"
        ]
      }
    }
  },
  "summary": "写真の温度と柔らかい余白を主役にした、ホスピタリティ冊子のようなサイト。",
  "mood": "温白 / 木肌 / 蒸気色",
  "accent": "招き入れる温度",
  "personality": "Welcoming, polished, human"
}
